icd_validator/__init__.py
icd_validator/validator.py
icd_validator-0.1.dist-info/METADATA
icd_validator-0.1.dist-info/WHEEL
icd_validator-0.1.dist-info/top_level.txt
icd_validator-0.1.dist-info/RECORD
